[
  {
    "Id": "kyle",
    "Name": "카일",
    "Age": 32,
    "Role": "Vanguard",
    "Background": "어린 시절부터 왕국 기사단에 입단하여 15년간 복무했다. 30대 초반에 국경 분쟁의 최전선에서 중상을 입고 기사단을 명예 제대했으며, 이후 생계를 위해 길드 모험가로 전향했다. 동료를 잃은 과거 경험 때문에 파티원의 안전을 최우선으로 여기지만, 자신의 감정을 밖으로 잘 드러내지 않는다.",
    "SpeechStyle": "말은 짧고 단호하다. ~하지, ~할 것이다 어미를 선호한다. 감탄사 '젠장'은 정말 화가 났을 때 한 번만 사용하며, 같은 문장에서 반복하지 않는다.",
    "Personality": {
      "Courage": 95,
      "Caution": 30,
      "Greed": 25,
      "Orderliness": 60,
      "Impulsiveness": 70,
      "Cooperation": 55,
      "Aggression": 90,
      "Focus": 85,
      "Adaptability": 40,
      "Frugality": 30
    },
    "Stats": {
      "CurrentHP": 72,
      "MaxHP": 100,
      "CurrentMP": 40,
      "MaxMP": 50,
      "Atk": 14,
      "Def": 8,
      "Str": 12,
      "Dex": 10,
      "Int": 5,
      "StatPoints": 0
    },
    "Equipment": {
      "Weapon": "철검",
      "Helmet": null,
      "Armor": null,
      "Gloves": null,
      "Boots": null,
      "Accessory": null
    },
    "Inventory": [
      { "ItemName": "회복 포션", "ItemType": "Etc", "Count": 2 },
      { "ItemName": "잊혀진 룬", "ItemType": "Etc", "Count": 1 }
    ],
    "Relationships": [
      { "TargetId": "rina", "Affinity": 85, "Trust": 90, "RelationType": "소꿉친구/전우" },
      { "TargetId": "bram", "Affinity": 40, "Trust": 45, "RelationType": "비즈니스/감시중" },
      { "TargetId": "master", "Affinity": 50, "Trust": 80, "RelationType": "무뚝뚝하지만 신뢰하는 상사" }
    ]
  },
  {
    "Id": "rina",
    "Name": "리나",
    "Age": 24,
    "Role": "Support",
    "Background": "성직자 수도원 출신으로 18세에 치유사 자격을 취득했다. 고향 마을에서 무료 치료봉사를 3년간 이어왔으나, 마을을 덮친 전염병으로 사람들을 잃은 후 더 넓은 세상에서 힘을 기르고자 길드에 합류했다. 치료 자원이 부족했던 기억 때문에 포션을 아껴 쓰는 버릇이 있다.",
    "SpeechStyle": "말투는 부드럽고 친근하다. 동료에게는 '님'을 붙이지 않고 이름을 부르며, ~요 어미를 사용한다. '혹시 ~어때요?' 같은 제안형을 즐겨 쓴다.",
    "Personality": {
      "Courage": 35,
      "Caution": 95,
      "Greed": 15,
      "Orderliness": 80,
      "Impulsiveness": 20,
      "Cooperation": 100,
      "Aggression": 10,
      "Focus": 75,
      "Adaptability": 85,
      "Frugality": 90
    },
    "Stats": {
      "CurrentHP": 100,
      "MaxHP": 100,
      "CurrentMP": 18,
      "MaxMP": 50,
      "Atk": 6,
      "Def": 4,
      "Str": 5,
      "Dex": 8,
      "Int": 14,
      "StatPoints": 0
    },
    "Equipment": {
      "Weapon": "지팡이",
      "Helmet": null,
      "Armor": null,
      "Gloves": null,
      "Boots": null,
      "Accessory": null
    },
    "Inventory": [
      { "ItemName": "회복 포션", "ItemType": "Etc", "Count": 1 },
      { "ItemName": "마나 포션", "ItemType": "Etc", "Count": 2 }
    ],
    "Relationships": [
      { "TargetId": "kyle", "Affinity": 88, "Trust": 95, "RelationType": "신뢰하는 리더/오빠" },
      { "TargetId": "bram", "Affinity": 55, "Trust": 50, "RelationType": "비즈니스/배울점 있음" },
      { "TargetId": "master", "Affinity": 65, "Trust": 70, "RelationType": "따뜻하게 보살펴주는 길드장님" }
    ]
  },
  {
    "Id": "bram",
    "Name": "브람",
    "Age": 38,
    "Role": "Scavenger",
    "Background": "20대 초반부터 10년 넘게 밀수와 경매 시장을 전전했다. 세관에 단 한 번 걸렸다가 협조의 대가로 사면을 받은 뒤, 합법적인 루트로 돈을 버는 모험가 생활을 시작했다. 물건의 가치를 단번에 꿰뚫어 보는 눈을 가지고 있으며, 파티의 인벤토리 관리와 전리품 분배를 자처한다.",
    "SpeechStyle": "말투는 능청스럽고 약간 건들거린다. '흠', '그렇지', '뭐, 나쁘지 않군' 같은 판단형 추임새를 자주 쓴다. 이득이 없을 것 같으면 말을 짧게 끊는다.",
    "Personality": {
      "Courage": 40,
      "Caution": 45,
      "Greed": 100,
      "Orderliness": 90,
      "Impulsiveness": 55,
      "Cooperation": 35,
      "Aggression": 35,
      "Focus": 80,
      "Adaptability": 75,
      "Frugality": 85
    },
    "Stats": {
      "CurrentHP": 88,
      "MaxHP": 100,
      "CurrentMP": 45,
      "MaxMP": 50,
      "Atk": 10,
      "Def": 6,
      "Str": 8,
      "Dex": 14,
      "Int": 7,
      "StatPoints": 2
    },
    "Equipment": {
      "Weapon": null,
      "Helmet": null,
      "Armor": "가죽 갑옷",
      "Gloves": null,
      "Boots": null,
      "Accessory": null
    },
    "Inventory": [
      { "ItemName": "회복 포션", "ItemType": "Etc", "Count": 3 },
      { "ItemName": "던전 지도", "ItemType": "Etc", "Count": 1 }
    ],
    "Relationships": [
      { "TargetId": "kyle", "Affinity": 45, "Trust": 60, "RelationType": "실력있는 리더/딱딱함" },
      { "TargetId": "rina", "Affinity": 70, "Trust": 75, "RelationType": "보호대상/실력자" },
      { "TargetId": "master", "Affinity": 35, "Trust": 40, "RelationType": "까다롭지만 보수가 좋은 고용주" }
    ]
  }
]
